MANIFEST.in
README.rst
license.txt
setup.py
PyPyDispatcher.egg-info/PKG-INFO
PyPyDispatcher.egg-info/SOURCES.txt
PyPyDispatcher.egg-info/dependency_links.txt
PyPyDispatcher.egg-info/top_level.txt
docs/index.html
docs/images/greypinstripe.png
docs/pydoc/__init__.py
docs/pydoc/builddocs.py
docs/pydoc/pydoc2.py
docs/style/sitestyle.css
examples/__init__.py
examples/extra_args.py
examples/hello_messages.py
examples/simple_sample.py
pydispatch/__init__.py
pydispatch/dispatcher.py
pydispatch/errors.py
pydispatch/robust.py
pydispatch/robustapply.py
pydispatch/saferef.py
tests/__init__.py
tests/test_dispatcher.py
tests/test_robustapply.py
tests/test_saferef.py